{"bm-master.db.zalando":{"total":373,"idle":359,"detail":{"connectionsByUser":{"aweber":{"conns":"3","idle":"3"},"postgres":{"conns":"2","idle":"0"},"rkoch":{"conns":"1","idle":"1"},"robot_catalog_migrator":{"conns":"8","idle":"6"},"robot_db_diff":{"conns":"1","idle":"0"},"robot_pgha":{"conns":"2","idle":"2"},"robot_video_upload":{"conns":"2","idle":"0"},"zomcat_p0120":{"conns":"7","idle":"7"},"zomcat_p4020":{"conns":"2","idle":"2"},"zomcat_p4420":{"conns":"97","idle":"97"},"zomcat_p8620":{"conns":"7","idle":"4"},"zomcat_p9820":{"conns":"241","idle":"237"}},"maxConnections":"500","server":"bm-master.db.zalando"},"maxConnections":"500"},"customer1-master.db.zalando":{"total":226,"idle":224,"detail":{"connectionsByUser":{"avaczi":{"conns":"1","idle":"1"},"nagios":{"conns":"1","idle":"1"},"perler":{"conns":"1","idle":"1"},"robot_db_diff":{"conns":"1","idle":"0"},"robot_order_cockpit":{"conns":"1","idle":"1"},"robot_pgha":{"conns":"2","idle":"2"},"zalando_plproxy_ro":{"conns":"3","idle":"3"},"zomcat_p0110":{"conns":"1","idle":"1"},"zomcat_p0120":{"conns":"55","idle":"55"},"zomcat_p0121":{"conns":"53","idle":"53"},"zomcat_p4025":{"conns":"7","idle":"6"},"zomcat_p9620":{"conns":"100","idle":"100"}},"maxConnections":"700","server":"customer1-master.db.zalando"},"maxConnections":"700"},"customer2-master.db.zalando":{"total":116,"idle":114,"detail":{"connectionsByUser":{"nagios":{"conns":"1","idle":"1"},"robot_db_diff":{"conns":"1","idle":"0"},"robot_pgha":{"conns":"2","idle":"2"},"tsarnowski":{"conns":"1","idle":"1"},"zalando_plproxy_ro":{"conns":"3","idle":"3"},"zomcat_p4025":{"conns":"6","idle":"6"},"zomcat_p9620":{"conns":"102","idle":"101"}},"maxConnections":"700","server":"customer2-master.db.zalando"},"maxConnections":"700"},"customer3-master.db.zalando":{"total":115,"idle":113,"detail":{"connectionsByUser":{"nagios":{"conns":"1","idle":"1"},"robot_db_diff":{"conns":"1","idle":"0"},"robot_pgha":{"conns":"2","idle":"2"},"zalando_plproxy_ro":{"conns":"3","idle":"3"},"zomcat_p4025":{"conns":"6","idle":"5"},"zomcat_p9620":{"conns":"102","idle":"102"}},"maxConnections":"700","server":"customer3-master.db.zalando"},"maxConnections":"700"},"customer4-master.db.zalando":{"total":122,"idle":120,"detail":{"connectionsByUser":{"nagios":{"conns":"1","idle":"1"},"robot_db_diff":{"conns":"1","idle":"0"},"robot_order_cockpit":{"conns":"1","idle":"1"},"robot_pgha":{"conns":"2","idle":"2"},"zalando_plproxy_ro":{"conns":"3","idle":"3"},"zomcat_p4025":{"conns":"6","idle":"5"},"zomcat_p9620":{"conns":"108","idle":"108"}},"maxConnections":"700","server":"customer4-master.db.zalando"},"maxConnections":"700"},"customer5-master.db.zalando":{"total":106,"idle":105,"detail":{"connectionsByUser":{"nagios":{"conns":"1","idle":"1"},"robot_db_diff":{"conns":"1","idle":"0"},"robot_pgha":{"conns":"2","idle":"2"},"zalando_plproxy_ro":{"conns":"1","idle":"1"},"zomcat_p4025":{"conns":"6","idle":"6"},"zomcat_p9620":{"conns":"95","idle":"95"}},"maxConnections":"700","server":"customer5-master.db.zalando"},"maxConnections":"700"},"customer6-master.db.zalando":{"total":103,"idle":101,"detail":{"connectionsByUser":{"nagios":{"conns":"1","idle":"1"},"robot_db_diff":{"conns":"1","idle":"0"},"robot_pgha":{"conns":"2","idle":"2"},"zalando_plproxy_ro":{"conns":"1","idle":"1"},"zomcat_p4025":{"conns":"6","idle":"5"},"zomcat_p9620":{"conns":"92","idle":"92"}},"maxConnections":"700","server":"customer6-master.db.zalando"},"maxConnections":"700"},"customer7-master.db.zalando":{"total":102,"idle":101,"detail":{"connectionsByUser":{"nagios":{"conns":"1","idle":"1"},"robot_db_diff":{"conns":"1","idle":"0"},"robot_pgha":{"conns":"2","idle":"2"},"zalando_plproxy_ro":{"conns":"1","idle":"1"},"zomcat_p4025":{"conns":"6","idle":"6"},"zomcat_p9620":{"conns":"91","idle":"91"}},"maxConnections":"700","server":"customer7-master.db.zalando"},"maxConnections":"700"},"customer8-master.db.zalando":{"total":101,"idle":100,"detail":{"connectionsByUser":{"nagios":{"conns":"1","idle":"1"},"robot_db_diff":{"conns":"1","idle":"0"},"robot_pgha":{"conns":"2","idle":"2"},"zalando_plproxy_ro":{"conns":"1","idle":"1"},"zomcat_p4025":{"conns":"6","idle":"6"},"zomcat_p9620":{"conns":"90","idle":"90"}},"maxConnections":"700","server":"customer8-master.db.zalando"},"maxConnections":"700"},"shop-master.db.zalando":{"total":664,"idle":663,"detail":{"connectionsByUser":{"amengele":{"conns":"1","idle":"1"},"robot_db_diff":{"conns":"1","idle":"0"},"robot_pgha":{"conns":"2","idle":"2"},"zomcat_p0110":{"conns":"4","idle":"4"},"zomcat_p0120":{"conns":"268","idle":"268"},"zomcat_p0121":{"conns":"253","idle":"253"},"zomcat_p0125":{"conns":"135","idle":"135"}},"maxConnections":"1000","server":"shop-master.db.zalando"},"maxConnections":"1000"},"customeridx-master.db.zalando":{"total":221,"idle":219,"detail":{"connectionsByUser":{"perler":{"conns":"2","idle":"2"},"robot_db_diff":{"conns":"1","idle":"0"},"robot_pgha":{"conns":"2","idle":"2"},"serverstats":{"conns":"1","idle":"0"},"zomcat_p9620":{"conns":"215","idle":"215"}},"maxConnections":"500","server":"customeridx-master.db.zalando"},"maxConnections":"500"},"ja-master.db.zalando":{"total":159,"idle":155,"detail":{"connectionsByUser":{"cpieper":{"conns":"1","idle":"1"},"robot_bucardo":{"conns":"2","idle":"2"},"robot_db_diff":{"conns":"1","idle":"0"},"robot_pgha":{"conns":"2","idle":"2"},"tberger":{"conns":"3","idle":"3"},"zomcat_p0120":{"conns":"4","idle":"4"},"zomcat_p4027":{"conns":"8","idle":"8"},"zomcat_p8120":{"conns":"1","idle":"1"},"zomcat_p9320":{"conns":"8","idle":"8"},"zomcat_p9420":{"conns":"9","idle":"9"},"zomcat_p9421":{"conns":"36","idle":"36"},"zomcat_p9520":{"conns":"23","idle":"23"},"zomcat_p9920":{"conns":"56","idle":"53"},"zomcat_p9925":{"conns":"5","idle":"5"}},"maxConnections":"500","server":"ja-master.db.zalando"},"maxConnections":"500"},"stock1.db.zalando":{"total":307,"idle":306,"detail":{"connectionsByUser":{"robot_db_diff":{"conns":"1","idle":"0"},"robot_pgha":{"conns":"2","idle":"2"},"tasyrkin":{"conns":"1","idle":"1"},"zomcat_p6420":{"conns":"303","idle":"303"}},"maxConnections":"500","server":"stock1.db.zalando"},"maxConnections":"500"},"stock5.db.zalando":{"total":285,"idle":284,"detail":{"connectionsByUser":{"robot_db_diff":{"conns":"1","idle":"0"},"robot_pgha":{"conns":"2","idle":"2"},"zomcat_p6420":{"conns":"282","idle":"282"}},"maxConnections":"500","server":"stock5.db.zalando"},"maxConnections":"500"},"payment.db.zalando":{"total":279,"idle":276,"detail":{"connectionsByUser":{"ahanin":{"conns":"4","idle":"3"},"ntillmann":{"conns":"5","idle":"5"},"postgres":{"conns":"1","idle":"0"},"rlinse":{"conns":"2","idle":"2"},"robot_db_diff":{"conns":"1","idle":"0"},"robot_pgha":{"conns":"2","idle":"2"},"tberger":{"conns":"2","idle":"2"},"zomcat_p6220":{"conns":"60","idle":"60"},"zomcat_p6320":{"conns":"93","idle":"93"},"zomcat_p9220":{"conns":"43","idle":"43"},"zomcat_p9820":{"conns":"66","idle":"66"}},"maxConnections":"500","server":"payment.db.zalando"},"maxConnections":"500"},"catalog1.db.zalando":{"total":157,"idle":0,"detail":{"connectionsByUser":{"cwolters":{"conns":"5","idle":"0"},"jsoick":{"conns":"1","idle":"0"},"robot_catalog_migrator":{"conns":"4","idle":"0"},"robot_db_diff":{"conns":"1","idle":"0"},"robot_pgha":{"conns":"2","idle":"0"},"zomcat_p7020":{"conns":"144","idle":"0"}},"maxConnections":"500","server":"catalog1.db.zalando"},"maxConnections":"500"}}